thecollector/__init__.py
thecollector/bagit.py
thecollector/circular_buffer.py
thecollector/data.py
thecollector/protocols.py
thecollector/utils.py
thecollector-0.8.4.dist-info/LICENSE
thecollector-0.8.4.dist-info/WHEEL
thecollector-0.8.4.dist-info/METADATA
thecollector-0.8.4.dist-info/RECORD
