Metadata-Version: 2.1
Name: thecollector
Version: 0.8.4
Summary: A library to store robot data in a msgpack format
Home-page: https://pypi.org/project/the-collector/
License: MIT
Keywords: library,robotics,robot,msgpack,storage,json,pickle
Author: walchko
Author-email: walchko@users.noreply.github.com
Requires-Python: >=3.6
Classifier: Development Status :: 4 - Beta
Classifier: Intended Audience :: Developers
Classifier: License :: OSI Approved :: MIT License
Classifier: Operating System :: OS Independent
Classifier: Programming Language :: Python :: 3
Classifier: Programming Language :: Python :: 3.6
Classifier: Programming Language :: Python :: 3.7
Classifier: Programming Language :: Python :: 3.8
Classifier: Topic :: Software Development :: Libraries
Classifier: Topic :: Software Development :: Libraries :: Application Frameworks
Classifier: Topic :: Software Development :: Libraries :: Python Modules
Requires-Dist: msgpack
Requires-Dist: simplejson
Project-URL: Repository, http://github.com/MomsFriendlyRobotCompany/the_collector
